{
    "gamejolt": {
        "game_id": "1085393",
        "builds": [
            {
                "package_id": "1109746",
                "release_id": "new",
                "path": "dist/krisis-knightmare-release-win64.zip",
                "platforms": ["windows_64"]
            },
            {
                "package_id": "1109746",
                "release_id": "new",
                "path": "dist/krisis-knightmare-release.love",
                "platforms": ["other"]
            },
            {
                "package_id": "1109746",
                "release_id": "new",
                "path": "dist/krisis-knightmare-mod.zip",
                "platforms": ["other"]
            }
        ]
    },
    "gamebanana": {
        "mod_id": "695877",
        "paths": [
            "dist/krisis-knightmare-mod.zip",
            "dist/krisis-knightmare-release-win64.zip"
        ]
    }
}
